nonebot_plugin_capoo/__init__.py
nonebot_plugin_capoo/config.py
nonebot_plugin_capoo/download.py
nonebot_plugin_capoo/sqlite.py
nonebot_plugin_capoo-0.1.5.dist-info/LICENSE
nonebot_plugin_capoo-0.1.5.dist-info/METADATA
nonebot_plugin_capoo-0.1.5.dist-info/WHEEL
nonebot_plugin_capoo-0.1.5.dist-info/RECORD
