Metadata-Version: 2.1
Name: nonebot-plugin-capoo
Version: 0.1.5
Summary: 一个发送 capoo 表情包的插件
Home-page: https://github.com/HuParry/nonebot-plugin-capoo
License: MIT
Author: HuParry
Author-email: huparry@outlook.com
Requires-Python: >=3.8
Classifier: License :: OSI Approved :: MIT License
Classifier: Programming Language :: Python :: 3
Classifier: Programming Language :: Python :: 3.8
Classifier: Programming Language :: Python :: 3.9
Classifier: Programming Language :: Python :: 3.10
Classifier: Programming Language :: Python :: 3.11
Classifier: Programming Language :: Python :: 3.12
Requires-Dist: asyncio (>=3.4.3)
Requires-Dist: httpx (>=0.20.0,<1.0.0)
Requires-Dist: nonebot-adapter-onebot (>=2.1.5)
Requires-Dist: nonebot2 (>=2.0.0)
Project-URL: Repository, https://github.com/HuParry/nonebot-plugin-capoo
